cmdline/CPdescripter.py
cmdline/CPdiel.py
cmdline/CPextract.py
cmdline/CPextract_old.py
cmdline/CPmake.py
cmdline/CPml.py
cmdline/CPml_mpi.py
cmdline/CPtrain.py
cmdline/__init__.py
cmdline/cpextract_cp.py
cmdline/cpextract_cpmd.py
cmdline/cpextract_diel.py
cmdline/cpmake_cpmd.py
cmdline/cpmake_diel.py
cmdline/cpmake_nose.py
cmdline/cpmake_smile.py
cmdline/cptrain_sample.py
cmdline/cptrain_test.py
cmdline/cptrain_train.py
cmdline/cptrain_train_io.py
cmdline/make_alm.py
cmdline/ml_predict.py
cmdline/nose_mass.py
cmdline/test.py
cpmd/__init__.py
cpmd/asign_wcs.py
cpmd/asign_wcs_torch.py
cpmd/class_atoms_wan.py
cpmd/class_atoms_wan_torch.py
cpmd/converter_cpmd.py
cpmd/descripter.py
cpmd/dipole_core.py
cpmd/gromacs_wrap.py
cpmd/make_gif.py
cpmd/read_core.py
cpmd/read_traj.py
cpmd/read_traj_cpmd.py
cpmd/read_wfc.py
cpmd/read_wfc_cpmd.py
cpmd/script.py
cpmd/show_CP.py
cpmd/show_XDATCAR.py
cpmd/test.py
cpmd/vdos.py
cpmd/test/__init__.py
cpmd/test/gromacs.py
data/__init__.py
diel/__init__.py
diel/acf_fourier.py
diel/dipole_core.py
diel/fit_diel.py
diel/vdos.py
include/__init__.py
include/constants.py
include/small.py
ml/__init__.py
ml/acf_fourier.py
ml/atomtype.py
ml/ml.py
ml/ml_dataset.py
ml/ml_dataset_old.py
ml/ml_loss.py
ml/ml_loss_nequip.py
ml/ml_plot.py
ml/ml_train.py
ml/ml_train_class.py
ml/ml_util.py
ml/mlmodel.py
ml/mlmodel_old.py
ml/molecule.py
ml/molecule_old.py
ml/parse.py
ml/dataset/__init__.py
ml/dataset/mldataset_abstract.py
ml/dataset/mldataset_descs.py
ml/dataset/mldataset_xyz.py
ml/model/__init__.py
ml/model/mlmodel.py
ml/model/mlmodel_abstract.py
ml/model/mlmodel_basic.py
quadrupole/__init__.py
quadrupole/bec.py
quadrupole/calc_acf.py
quadrupole/calc_fourier.py
quadrupole/load_traj.py
quadrupole/plot.py
quadrupole/plot_diel.py
quadrupole/yamazaki.py
MLWC-0.1.0.dist-info/LICENSE
MLWC-0.1.0.dist-info/METADATA
MLWC-0.1.0.dist-info/WHEEL
MLWC-0.1.0.dist-info/entry_points.txt
MLWC-0.1.0.dist-info/top_level.txt
MLWC-0.1.0.dist-info/RECORD
