Metadata-Version: 2.1
Name: MLWC
Version: 0.1.0
Summary: MMLWC (machine learning Wannier center)
Home-page: https://github.com/ToAmano/MLWC
Download-URL: https://github.com/ToAmano/MLWC
Author: Tomohito Amano, Tamio Yamazaki
Author-email: amanotomohito040@gmail.com
License: file : LICENSE
License-File: LICENSE
Requires-Dist: numpy
Requires-Dist: ase ==3.23.0
Requires-Dist: mdtraj ==1.9.9
Requires-Dist: nglview
Requires-Dist: moviepy
Requires-Dist: torch >=2.2.0
Requires-Dist: rdkit >=2023.03.1
Requires-Dist: pyyaml
Requires-Dist: statsmodels
Requires-Dist: torchinfo
Requires-Dist: joblib ==1.2.0
Requires-Dist: matplotlib
